folioprompts/__init__.py
folioprompts/folio.db
folioprompts/folio.py
folioprompts/main.py
folioprompts/prompts/ner/1
folioprompts/prompts/ner/2
folioprompts/prompts/ner/3
folioprompts/prompts/ner/latest
folioprompts/prompts/ner_2/1
folioprompts/prompts/ner_2/latest
folioprompts/prompts/say_hello/2
folioprompts/prompts/say_hello/latest
folioprompts/template_renderer.py
folioprompts-0.2.0.dist-info/METADATA
folioprompts-0.2.0.dist-info/WHEEL
folioprompts-0.2.0.dist-info/entry_points.txt
folioprompts-0.2.0.dist-info/RECORD
