Metadata-Version: 2.1
Name: folioprompts
Version: 0.2.0
Summary: 
Author: Ganesh Katrapati
Author-email: neshmailsu@gmail.com
Requires-Python: >=3.9,<4.0
Classifier: Programming Language :: Python :: 3
Classifier: Programming Language :: Python :: 3.9
Classifier: Programming Language :: Python :: 3.10
Classifier: Programming Language :: Python :: 3.11
Classifier: Programming Language :: Python :: 3.12
Classifier: Programming Language :: Python :: 3.13
Requires-Dist: jinja2 (>=3.1.4,<4.0.0)
Requires-Dist: pydantic (>=2.9.2,<3.0.0)
Requires-Dist: rich (>=13.9.3,<14.0.0)
Requires-Dist: tinydb (>=4.8.2,<5.0.0)
Requires-Dist: typer (>=0.12.5,<0.13.0)
